{
  "Descriptor": {
    "UId": "65d4b9b2-8308-4847-cec5-cc3bba7dfb3a",
    "Name": "UsrYachtStatus_Value",
    "ModifiedOnUtc": "\/Date(1761287761000)\/",
    "InstallType": 0,
    "Schema": {
      "UId": "42c3f482-602f-48d0-9bab-2d02c0122456",
      "Name": "UsrYachtStatus"
    },
    "Columns": [
      {
        "ColumnUId": "9e53fd7c-dde4-4502-a64c-b9e34148108b",
        "IsForceUpdate": false,
        "IsKey": false,
        "ColumnName": "Description",
        "DataTypeValueUId": "ddb3a1ee-07e8-4d62-b7a9-d0e618b00fbd"
      },
      {
        "ColumnUId": "50812832-49ce-a2a1-181a-aae952088409",
        "IsForceUpdate": true,
        "IsKey": false,
        "ColumnName": "UsrMyColor",
        "DataTypeValueUId": "dafb71f9-ee9f-4e0b-a4d7-37aa15987155"
      },
      {
        "ColumnUId": "e80190a5-03b2-4095-90f7-a193a960adee",
        "IsForceUpdate": false,
        "IsKey": false,
        "ColumnName": "CreatedOn",
        "DataTypeValueUId": "d21e9ef4-c064-4012-b286-fa1a8171da44"
      },
      {
        "ColumnUId": "736c30a7-c0ec-4fa9-b034-2552b319b633",
        "IsForceUpdate": true,
        "IsKey": false,
        "ColumnName": "Name",
        "DataTypeValueUId": "ddb3a1ee-07e8-4d62-b7a9-d0e618b00fbd"
      },
      {
        "ColumnUId": "ae0e45ca-c495-4fe7-a39d-3ab7278e1617",
        "IsForceUpdate": false,
        "IsKey": true,
        "ColumnName": "Id",
        "DataTypeValueUId": "23018567-a13c-4320-8687-fd6f9e3699bd"
      }
    ]
  }
}